laipvt/__init__.py
laipvt/cli/__init__.py
laipvt/cli/delete.py
laipvt/cli/deploy.py
laipvt/cli/main.py
laipvt/cli/mysql_restore.py
laipvt/cli/poc.py
laipvt/controller/kubernetes/kube.py
laipvt/controller/middleware/elasticsearch.py
laipvt/controller/middleware/etcd.py
laipvt/controller/middleware/etcd_k8s.py
laipvt/controller/middleware/harbor.py
laipvt/controller/middleware/identity.py
laipvt/controller/middleware/keepalived.py
laipvt/controller/middleware/minio.py
laipvt/controller/middleware/monitor.py
laipvt/controller/middleware/mysql.py
laipvt/controller/middleware/mysql_k8s.py
laipvt/controller/middleware/nacos.py
laipvt/controller/middleware/nfs.py
laipvt/controller/middleware/nginx.py
laipvt/controller/middleware/pgsql.py
laipvt/controller/middleware/rabbitmq.py
laipvt/controller/middleware/redis.py
laipvt/controller/middleware/redis_k8s.py
laipvt/controller/middleware/siber.py
laipvt/controller/middleware/nacos_files/environment_config.conf
laipvt/controller/middleware/nacos_files/grpc_services.conf
laipvt/controller/middleware/nacos_files/middleware.conf
laipvt/controller/service/captcha.py
laipvt/controller/service/chatbot.py
laipvt/controller/service/commander.py
laipvt/controller/service/common_service.py
laipvt/controller/service/dataservice.py
laipvt/controller/service/entbs.py
laipvt/controller/service/entcc.py
laipvt/controller/service/entiap.py
laipvt/controller/service/iapcloud.py
laipvt/controller/service/license.py
laipvt/controller/service/mage.py
laipvt/controller/service/nlp.py
laipvt/controller/service/nlp_layoutlm.py
laipvt/controller/service/notice.py
laipvt/controller/service/ocr.py
laipvt/controller/service/ocr_bizlicense.py
laipvt/controller/service/ocr_idcard_server.py
laipvt/controller/service/ocr_layout_analysis.py
laipvt/controller/service/ocr_standard.py
laipvt/controller/service/ocr_table.py
laipvt/controller/service/ocr_text.py
laipvt/controller/service/ocr_text_cpu.py
laipvt/controller/service/rpa_collaboration.py
laipvt-3.0.4.dist-info/LICENSE
laipvt-3.0.4.dist-info/METADATA
laipvt-3.0.4.dist-info/WHEEL
laipvt-3.0.4.dist-info/entry_points.txt
laipvt-3.0.4.dist-info/top_level.txt
laipvt-3.0.4.dist-info/RECORD
